snips_skill_spelling-0.0.2.dist-info/DESCRIPTION.rst
snips_skill_spelling-0.0.2.dist-info/METADATA
snips_skill_spelling-0.0.2.dist-info/RECORD
snips_skill_spelling-0.0.2.dist-info/WHEEL
snips_skill_spelling-0.0.2.dist-info/metadata.json
snips_skill_spelling-0.0.2.dist-info/top_level.txt
spellingskill/Snipsspec
spellingskill/__init__.py
spellingskill/spellingskill.py
