Metadata-Version: 2.0
Name: snips-skill-spelling
Version: 0.0.2
Summary: answer spelling questions
Home-page: UNKNOWN
Author: steve ryan
Author-email: stever@syntithenai.com
License: MIT
Keywords: snips
Platform: UNKNOWN
